btbpython/__init__.py
btbpython/client.py
btbpython/lyrics.py
btbpython/madlibs.py
btbpython/meme.py
btbpython/reddit.py
btbpython/text.py
btbpython/word.py
btbpython-2.1.1.dist-info/LICENSE
btbpython-2.1.1.dist-info/METADATA
btbpython-2.1.1.dist-info/WHEEL
btbpython-2.1.1.dist-info/top_level.txt
btbpython-2.1.1.dist-info/RECORD
