Metadata-Version: 2.1
Name: btbpython
Version: 2.1.1
Summary: A feature rich API to interact with the BttesToBits API
Home-page: https://github.com/Pug234/btb.py
Author: Corbin McKEe
Author-email: corbin.mckee.ryan@gmail.com
License: MIT
Keywords: API,BtbAPI,py,python,APIWrapper,btb.py,btb,BytesToBits
Platform: UNKNOWN
Classifier: Intended Audience :: Developers
Classifier: Topic :: Software Development :: Build Tools
Classifier: License :: OSI Approved :: MIT License
Classifier: Programming Language :: Python :: 3.6
Classifier: Programming Language :: Python :: 3.7
Classifier: Programming Language :: Python :: 3.8
Classifier: Programming Language :: Python :: 3.9
Requires-Dist: requests
Requires-Dist: Pillow
